llama_integration/__init__.py
llama_integration/api-key-manager.py
llama_integration/base-provider.py
llama_integration/config.py
llama_integration/core.py
llama_integration/coreml-conversion.py
llama_integration/gateway-implementation.py
llama_integration/hipaa-masking.py
llama_integration/mlx-router.py
llama_integration/openai-provider.py
llama_integration/tee-integration.py
llama_integration/logging/audit.py
llama_integration/routing/strategies.py
llama_integration/utils/config.py
llama_integration-0.1.0.dist-info/METADATA
llama_integration-0.1.0.dist-info/WHEEL
llama_integration-0.1.0.dist-info/licenses/LICENSE
llama_integration-0.1.0.dist-info/RECORD
