Metadata-Version: 2.4
Name: llama-integration
Version: 0.1.0
Summary: Unified interface for multiple LLM providers with advanced features (routing, privacy, logging).
Project-URL: Homepage, https://github.com/yourusername/llamasearchai-git2-copy
Project-URL: Bug Tracker, https://github.com/yourusername/llamasearchai-git2-copy/issues
Author-email: Your Name / Llama Team <your.email@example.com>
License: MIT
License-File: LICENSE
Keywords: ai,anthropic,gateway,integration,llm,openai,privacy,routing
Classifier: Development Status :: 3 - Alpha
Classifier: Intended Audience :: Developers
Classifier: License :: OSI Approved :: MIT License
Classifier: Programming Language :: Python :: 3
Classifier: Programming Language :: Python :: 3.8
Classifier: Programming Language :: Python :: 3.9
Classifier: Programming Language :: Python :: 3.10
Classifier: Programming Language :: Python :: 3.11
Classifier: Topic :: Software Development :: Libraries :: Python Modules
Requires-Python: >=3.8
Requires-Dist: aiohttp>=3.8.0
Requires-Dist: cryptography>=39.0.0
Requires-Dist: loguru>=0.7.0
Requires-Dist: numpy>=1.20.0
Requires-Dist: pydantic>=2.0.0
Requires-Dist: pyyaml>=6.0
Requires-Dist: typing-extensions>=4.0.0
Provides-Extra: dev
Requires-Dist: black>=23.0.0; extra == 'dev'
Requires-Dist: isort>=5.12.0; extra == 'dev'
Requires-Dist: mypy>=1.0.0; extra == 'dev'
Requires-Dist: pylint>=2.17.0; extra == 'dev'
Requires-Dist: pytest-asyncio>=0.20.0; extra == 'dev'
Requires-Dist: pytest-cov>=4.0.0; extra == 'dev'
Requires-Dist: pytest-mock>=3.10.0; extra == 'dev'
Requires-Dist: pytest>=7.0.0; extra == 'dev'
Requires-Dist: sphinx-rtd-theme>=1.2.0; extra == 'dev'
Requires-Dist: sphinx>=6.0.0; extra == 'dev'
